ambient/__init__.py
ambient/ambient.py
ambient/backfill.py
ambient/cli.py
ambient_archiver-0.3.0.dist-info/LICENSE
ambient_archiver-0.3.0.dist-info/METADATA
ambient_archiver-0.3.0.dist-info/WHEEL
ambient_archiver-0.3.0.dist-info/entry_points.txt
ambient_archiver-0.3.0.dist-info/top_level.txt
ambient_archiver-0.3.0.dist-info/RECORD
