Metadata-Version: 2.1
Name: ambient-archiver
Version: 0.3.0
Summary: Archive your data from ambientweather.net
Home-page: https://github.com/mikepqr/ambient-archiver
Author: Mike Lee Williams
Author-email: mike@mike.place
Project-URL: Bug Reports, https://github.com/mikepqr/ambient-archiver/issues
Project-URL: Source, https://github.com/mikepqr/ambient-archiver
Keywords: weather
Classifier: Development Status :: 4 - Beta
Classifier: Environment :: Console
Classifier: Topic :: Utilities
Classifier: License :: OSI Approved :: MIT License
Classifier: Programming Language :: Python :: 3
Classifier: Programming Language :: Python :: 3.7
Classifier: Programming Language :: Python :: 3.8
Classifier: Programming Language :: Python :: 3.9
Classifier: Programming Language :: Python :: 3.10
Classifier: Programming Language :: Python :: 3.11
Classifier: Programming Language :: Python :: 3 :: Only
Requires-Python: >=3.9
License-File: LICENSE
Requires-Dist: requests
Requires-Dist: click
Provides-Extra: dev
Requires-Dist: types-requests ; extra == 'dev'
